emoji/__init__.py
emoji/aliases.py
emoji/unicodes.py
emojidb-0.0.2.dist-info/LICENSE
emojidb-0.0.2.dist-info/METADATA
emojidb-0.0.2.dist-info/WHEEL
emojidb-0.0.2.dist-info/top_level.txt
emojidb-0.0.2.dist-info/RECORD
