Metadata-Version: 2.1
Name: emojidb
Version: 0.0.2
Summary: Emoji DB package
Home-page: https://github.com/jameszhan/emojidb
Author: James Zhan
Author-email: zhiqiangzhan@gmail.com
Classifier: Programming Language :: Python :: 3
Classifier: License :: OSI Approved :: MIT License
Classifier: Operating System :: OS Independent
Requires-Python: >=3.0
License-File: LICENSE
